encryptcontent/__init__.py
encryptcontent/decrypt-form.tpl.html
encryptcontent/plugin.py
mkdocs_encryptcontent_plugin_gw-0.0.3.2.dist-info/LICENSE.md
mkdocs_encryptcontent_plugin_gw-0.0.3.2.dist-info/METADATA
mkdocs_encryptcontent_plugin_gw-0.0.3.2.dist-info/WHEEL
mkdocs_encryptcontent_plugin_gw-0.0.3.2.dist-info/entry_points.txt
mkdocs_encryptcontent_plugin_gw-0.0.3.2.dist-info/top_level.txt
mkdocs_encryptcontent_plugin_gw-0.0.3.2.dist-info/RECORD
