Metadata-Version: 2.1
Name: mkdocs-encryptcontent-plugin-gw
Version: 0.0.3.2
Summary: A fork of MkDocs plugin that encrypt/decrypt markdown content with AES
Home-page: https://github.com/greg-witczak/mkdocs-encryptcontent-plugin-gw
Author: greg-witczak
Author-email: gogowitczak@gmail.com
License: MIT
Download-URL: https://github.com/greg-witczak/mkdocs-encryptcontent-plugin-gw/archive/0.0.3.2.tar.gz
Keywords: mkdocs python markdown encrypt decrypt content
Platform: UNKNOWN
Classifier: Development Status :: 5 - Production/Stable
Classifier: Intended Audience :: Developers
Classifier: Intended Audience :: Information Technology
Classifier: License :: OSI Approved :: MIT License
Classifier: Programming Language :: Python
Classifier: Programming Language :: Python :: 2
Classifier: Programming Language :: Python :: 2.7
Classifier: Programming Language :: Python :: 3
Classifier: Programming Language :: Python :: 3.4
Classifier: Programming Language :: Python :: 3.5
Classifier: Programming Language :: Python :: 3.6
Classifier: Programming Language :: Python :: 3.7
Requires-Python: >=2.7.9,!=3.0.*,!=3.1.*,!=3.2.*,!=3.3.*
Requires-Dist: mkdocs
Requires-Dist: pyyaml
Requires-Dist: pycryptodome
